palace.cpython-36m-x86_64-linux-gnu.so
palace-0.2.5.dist-info/LICENSE
palace-0.2.5.dist-info/METADATA
palace-0.2.5.dist-info/top_level.txt
palace-0.2.5.dist-info/RECORD
palace-0.2.5.dist-info/WHEEL
palace.libs/libvorbisenc-93aef8ee.so.2.0.11
palace.libs/libvorbis-86113e64.so.0.4.8
palace.libs/libopus-37a3229e.so.0.5.3
palace.libs/libopusfile-e3fec9d9.so.0.4.1
palace.libs/libFLAC-9bf69166.so.8.3.0
palace.libs/libogg-b6ceea65.so.0.8.2
palace.libs/libvorbisfile-5692671f.so.3.3.7
palace.libs/libopenal-6f05a3bf.so.1.21.1
palace.libs/libsndfile-2411d765.so.1.0.27
palace.libs/libatomic-f8a74d6e.so.1.2.0
palace.libs/libalure2-af7d9726.so
