Metadata-Version: 2.1
Name: palace
Version: 0.2.5
Summary: Pythonic Audio Library and Codecs Environment
Home-page: https://mcsinyx.gitlab.io/palace
Author: Nguyễn Gia Phong
Author-email: ~cnx/palace@lists.sr.ht
License: LGPLv3+
Keywords: openal,alure,hrtf
Platform: UNKNOWN
Classifier: Development Status :: 4 - Beta
Classifier: Intended Audience :: Developers
Classifier: License :: OSI Approved :: GNU Lesser General Public License v3 or later (LGPLv3+)
Classifier: Operating System :: POSIX :: Linux
Classifier: Programming Language :: C++
Classifier: Programming Language :: Cython
Classifier: Programming Language :: Python :: 3.6
Classifier: Programming Language :: Python :: 3.7
Classifier: Programming Language :: Python :: 3.8
Classifier: Programming Language :: Python :: 3.9
Classifier: Programming Language :: Python :: 3 :: Only
Classifier: Topic :: Multimedia :: Sound/Audio
Classifier: Topic :: Software Development :: Libraries
Classifier: Typing :: Typed
Requires-Python: >=3.6
Requires-Dist: typing-extensions ; python_version < "3.8"
